customgpt_metrics/__init__.py
customgpt_metrics/adapters/__init__.py
customgpt_metrics/adapters/metric_adapter.py
customgpt_metrics/adapters/open_telemetry_adapter.py
customgpt_metrics/adapters/sql_adapter.py
customgpt_metrics/adapters/types/__init__.py
customgpt_metrics/adapters/types/log_entry.py
customgpt_metrics/adapters/types/metric.py
customgpt_metrics/metrics/__init__.py
customgpt_metrics/metrics/base_metric.py
customgpt_metrics/metrics/context_metric.py
customgpt_metrics/metrics/emotion_metric.py
customgpt_metrics/metrics/intent_metric.py
customgpt_metrics/metrics/language_metric.py
customgpt_metrics/metrics/model_provider/__init__.py
customgpt_metrics/metrics/model_provider/model_provider.py
customgpt_metrics/metrics/model_provider/strategy/__init__.py
customgpt_metrics/metrics/model_provider/strategy/azure_strategy.py
customgpt_metrics/metrics/model_provider/strategy/model_strategy.py
customgpt_metrics/metrics/model_provider/strategy/openai_strategy.py
customgpt_metrics/metrics/utils/__init__.py
customgpt_metrics-0.1.9.dist-info/METADATA
customgpt_metrics-0.1.9.dist-info/WHEEL
customgpt_metrics-0.1.9.dist-info/RECORD
