Metadata-Version: 2.1
Name: customgpt-metrics
Version: 0.1.9
Summary: Allow users to calculate RAG metrics
Author: authentichamza
Author-email: hamzashams446@gmail.com
Requires-Python: >=3.8,<4.0
Classifier: Programming Language :: Python :: 3
Classifier: Programming Language :: Python :: 3.8
Classifier: Programming Language :: Python :: 3.9
Classifier: Programming Language :: Python :: 3.10
Classifier: Programming Language :: Python :: 3.11
Requires-Dist: openai (>=0.28.1,<0.29.0)
Requires-Dist: pymysql (==1.0.3)
Requires-Dist: tiktoken (>=0.5.1,<0.6.0)
